ktis_parser/__init__.py
ktis_parser/ktis_parser.py
ktis_parser-0.3.1.dist-info/LICENSE
ktis_parser-0.3.1.dist-info/METADATA
ktis_parser-0.3.1.dist-info/WHEEL
ktis_parser-0.3.1.dist-info/top_level.txt
ktis_parser-0.3.1.dist-info/RECORD
