Metadata-Version: 2.1
Name: ktis-parser
Version: 0.3.1
Summary: ktis_parser default information parser
Home-page: https://github.com/zaeval/ktis_parser
Author: zaeval
Author-email: zaeval@kookmin.ac.kr
License: GPL
Platform: UNKNOWN
Classifier: Programming Language :: Python :: 3
Classifier: Operating System :: OS Independent
